{
  "day": 3,
  "text": "Мы пробовали сбиться.\nМеняли шаг.\nМеняли тон.\nДень смотрел.\nНо не отпускал.",
  "choices": {
    "A": {
      "label": "Спросить прямо: «Ты тоже всё помнишь?»",
      "effects": { "A": 1, "B": -1 },
      "afterText": "Вопрос повис, как световая царапина на плёнке.\nТы кивнула.\nИ вдруг стало легче — потому что мы больше не одни в этом."
    },
    "B": {
      "label": "Не спрашивать. Дать ей первой произнести это вслух.",
      "effects": { "A": -1, "B": 1 },
      "afterText": "Я выдержал паузу.\nИ в этой паузе ты сама сказала:\n«Я тоже… помню».\nКадр дрогнул, будто услышал своё имя."
    }
  }
}
